Metadata-Version: 2.1
Name: aipotheosislabs
Version: 0.0.1b3
Summary: The official Python SDK for the Aipolabs (Aipotheosis Labs) API
Home-page: https://aipolabs.xyz
Author: Aipolabs
Author-email: team@aipolabs.xyz
Requires-Python: >=3.10,<4.0
Classifier: Development Status :: 4 - Beta
Classifier: Intended Audience :: Developers
Classifier: Operating System :: MacOS
Classifier: Operating System :: Microsoft :: Windows
Classifier: Operating System :: OS Independent
Classifier: Operating System :: POSIX
Classifier: Operating System :: POSIX :: Linux
Classifier: Programming Language :: Python :: 3
Classifier: Programming Language :: Python :: 3.10
Classifier: Programming Language :: Python :: 3.11
Classifier: Programming Language :: Python :: 3.12
Classifier: Programming Language :: Python :: 3.13
Classifier: Topic :: Software Development :: Libraries :: Python Modules
Classifier: Typing :: Typed
Requires-Dist: httpx (>=0.27.2,<0.28.0)
Requires-Dist: pydantic (>=2.9.2,<3.0.0)
Requires-Dist: tenacity (>=9.0.0,<10.0.0)
Requires-Dist: typing-extensions (>=4.12.0,<5.0.0)
Project-URL: Repository, https://github.com/aipotheosis-labs/aipolabs-python
